recnys/__init__.py
recnys/backend/__init__.py
recnys/backend/state.py
recnys/backend/syncer.py
recnys/backend/task.py
recnys/backend/utils.py
recnys/frontend/__init__.py
recnys/frontend/load.py
recnys/frontend/parse.py
recnys/frontend/task.py
recnys/main.py
recnys/testing/backend/__init__.py
recnys/testing/backend/constants.py
recnys/testing/backend/utils.py
recnys/testing/frontend/__init__.py
recnys/testing/frontend/constants.py
recnys/testing/frontend/utils.py
recnys/testing/integration/__init__.py
recnys/testing/integration/constants.py
recnys/testing/integration/utils.py
recnys-0.3.0.dist-info/WHEEL
recnys-0.3.0.dist-info/entry_points.txt
recnys-0.3.0.dist-info/METADATA
recnys-0.3.0.dist-info/RECORD
