Metadata-Version: 2.3
Name: recnys
Version: 0.3.0
Summary: A simple dotfile synchronization helper
Author: VioletsOleander
Author-email: VioletsOleander <1377232072@qq.com>
Requires-Dist: pyyaml>=6.0.3
Requires-Python: >=3.14
